{"B9 TRIBECA":{"SUV":{"3":{"4":{"AS5":{"Z":{"c":"13.3","co2":"267","h":"9.5"}}}}}},"FORESTER 2.5X":{"SUV":{"2.5":{"4":{"A4":{"X":{"c":"10.4","co2":"212","h":"7.7"}},"M5":{"X":{"c":"10.7","co2":"214","h":"7.5"}}}}}},"FORESTER 2.5XS":{"SUV":{"2.5":{"4":{"A4":{"X":{"c":"10.4","co2":"212","h":"7.7"}},"M5":{"X":{"c":"10.7","co2":"214","h":"7.5"}}}}}},"FORESTER 2.5XT":{"SUV":{"2.5":{"4":{"M5":{"Z":{"c":"11.4","co2":"232","h":"8.5"}},"M6":{"Z":{"c":"11.7","co2":"230","h":"8"}}}}}},"IMPREZA 2.5I":{"SUBCOMPACT":{"2.5":{"4":{"A4":{"X":{"c":"10.4","co2":"212","h":"7.7"}},"M5":{"X":{"c":"10.7","co2":"214","h":"7.5"}}}}}},"IMPREZA 2.5I SPORT WAGON":{"STATION WAGON - SMALL":{"2.5":{"4":{"A4":{"X":{"c":"10.4","co2":"212","h":"7.7"}},"M5":{"X":{"c":"10.7","co2":"214","h":"7.5"}}}}}},"IMPREZA WRX":{"SUBCOMPACT":{"2.5":{"4":{"M5":{"Z":{"c":"11.7","co2":"230","h":"8"}}}}}},"IMPREZA WRX SPORT WAGON":{"STATION WAGON - SMALL":{"2.5":{"4":{"M5":{"Z":{"c":"11.7","co2":"230","h":"8"}}}}}},"IMPREZA WRX STI":{"SUBCOMPACT":{"2.5":{"4":{"M6":{"Z":{"c":"12.6","co2":"251","h":"8.8"}}}}}},"LEGACY 2.5GT":{"COMPACT":{"2.5":{"4":{"AS5":{"Z":{"c":"12.1","co2":"242","h":"8.6"}},"M5":{"Z":{"c":"11.7","co2":"230","h":"8"}}}}}},"LEGACY 2.5GT SPEC B":{"COMPACT":{"2.5":{"4":{"M6":{"Z":{"c":"12.3","co2":"242","h":"8.2"}}}}}},"LEGACY 2.5GT WAGON":{"STATION WAGON - MID-SIZE":{"2.5":{"4":{"AS5":{"Z":{"c":"12.1","co2":"242","h":"8.6"}},"M5":{"Z":{"c":"11.7","co2":"230","h":"8"}}}}}},"LEGACY 2.5I":{"COMPACT":{"2.5":{"4":{"AS4":{"X":{"c":"10.3","co2":"205","h":"7.2"}},"M5":{"X":{"c":"10.7","co2":"214","h":"7.5"}}}}},"STATION WAGON - MID-SIZE":{"2.5":{"4":{"AS4":{"X":{"c":"10.3","co2":"205","h":"7.2"}},"M5":{"X":{"c":"10.7","co2":"214","h":"7.5"}}}}}},"OUTBACK 2.5I WAGON":{"SUV":{"2.5":{"4":{"AS4":{"X":{"c":"10.6","co2":"214","h":"7.6"}},"M5":{"X":{"c":"10.3","co2":"209","h":"7.6"}}}}}},"OUTBACK 2.5XT WAGON":{"SUV":{"2.5":{"4":{"AS5":{"Z":{"c":"11.7","co2":"235","h":"8.4"}},"M5":{"Z":{"c":"11.3","co2":"228","h":"8.1"}}}}}},"OUTBACK 3.0R WAGON":{"SUV":{"3":{"4":{"AS5":{"Z":{"c":"12.2","co2":"242","h":"8.5"}}}}}}}