{"name":"Dolbeau-Mistassini, Quebec","structures":[{"name":"Apartment structures of six units and over","units":[{"name":"Bachelor units","prices":[179,178,183,192,496,null,null,null,null,null,null,null,null,null,null,null,null,null,null,260,266,269,null,null,null,273,273,284]},{"name":"One bedroom units","prices":[268,259,274,267,389,260,null,278,265,272,null,null,null,283,null,null,null,null,null,320,316,342,352,372,380,325,346,356]},{"name":"Two bedroom units","prices":[300,303,307,312,335,314,335,334,333,340,345,368,368,358,376,398,null,379,null,392,419,418,470,474,478,426,445,446]},{"name":"Three bedroom units","prices":[314,326,320,345,357,373,376,376,378,373,366,380,381,390,392,392,null,406,405,447,446,466,451,464,477,433,434,461]}]}]}